PyBindTest/__init__.py
PyBindTest/_core.cp311-win_amd64.pyd
pybindtest-0.0.2.dist-info/METADATA
pybindtest-0.0.2.dist-info/WHEEL
pybindtest-0.0.2.dist-info/entry_points.txt
pybindtest-0.0.2.dist-info/licenses/LICENSE
pybindtest-0.0.2.dist-info/RECORD
