Metadata-Version: 2.1
Name: PyBindTest
Version: 0.0.2
Summary: A minimal example package with pybind11
Author-Email: Whl <whl2075928012@gmail.com>
Classifier: Development Status :: 4 - Beta
Classifier: License :: OSI Approved :: MIT License
Classifier: Programming Language :: Python :: 3 :: Only
Classifier: Programming Language :: Python :: 3.7
Classifier: Programming Language :: Python :: 3.8
Classifier: Programming Language :: Python :: 3.9
Classifier: Programming Language :: Python :: 3.10
Classifier: Programming Language :: Python :: 3.11
Classifier: Programming Language :: Python :: 3.12
Requires-Python: >=3.7
Provides-Extra: test
Requires-Dist: pytest; extra == "test"
License-File: LICENSE
